[{"ks": [7, 7, 3, 7], "e": [6, 3, 3, 4], "d": [3], "Acc@1": 38.44444444444444, "latency": 0, "energy": 0, "net_id": "net_evo_10_0"}, {"ks": [7, 7, 3, 7], "e": [6, 3, 3, 4], "d": [3], "Acc@1": 38.44444444444444, "latency": 0, "energy": 0, "net_id": "net_evo_10_1"}, {"ks": [7, 7, 3, 7], "e": [6, 3, 3, 4], "d": [3], "Acc@1": 38.44444444444444, "latency": 0, "energy": 0, "net_id": "net_evo_10_2"}, {"ks": [7, 7, 3, 7], "e": [6, 3, 3, 4], "d": [3], "Acc@1": 38.44444444444444, "latency": 0, "energy": 0, "net_id": "net_evo_10_3"}, {"ks": [7, 7, 3, 7], "e": [6, 3, 3, 4], "d": [3], "Acc@1": 38.44444444444444, "latency": 0, "energy": 0, "net_id": "net_evo_10_4"}, {"ks": [7, 7, 3, 7], "e": [6, 3, 3, 4], "d": [3], "Acc@1": 38.44444444444444, "latency": 0, "energy": 0, "net_id": "net_evo_10_5"}, {"ks": [7, 7, 3, 7], "e": [6, 3, 3, 4], "d": [3], "Acc@1": 38.44444444444444, "latency": 0, "energy": 0, "net_id": "net_evo_10_6"}, {"ks": [7, 7, 3, 7], "e": [6, 3, 3, 4], "d": [3], "Acc@1": 38.44444444444444, "latency": 0, "energy": 0, "net_id": "net_evo_10_7"}]